furl/__init__.py
furl/__version__.py
furl/common.py
furl/compat.py
furl/furl.py
furl/omdict1D.py
furl-2.1.2.dist-info/LICENSE.txt
furl-2.1.2.dist-info/METADATA
furl-2.1.2.dist-info/RECORD
furl-2.1.2.dist-info/WHEEL
furl-2.1.2.dist-info/top_level.txt
